setup.cfg
setup.py
logerator/__init__.py
logerator/logerator.py
logerator.egg-info/PKG-INFO
logerator.egg-info/SOURCES.txt
logerator.egg-info/dependency_links.txt
logerator.egg-info/requires.txt
logerator.egg-info/top_level.txt