Metadata-Version: 1.1
Name: logerator
Version: 0.4
Summary: A Python package that contains the decorator, before_and_after. The decorator implements before and after event logging using the Python Logentries package.
Home-page: https://github.com/reselbob/logerator
Author: Bob Reselman
Author-email: reselbob@gmail.com
License: MIT license
Download-URL: https://github.com/reselbob/logerator/archive/0.1.tar.gz
Keywords: logerator,logging,logentries
Platform: UNKNOWN
